{
  "name": {
    "literal": "Rachid"
  },
  "ai": {
    "type": "rct",
    "data": {
      "moveBias": 1,
      "switchBias": 0.5,
      "statMoveBias": 1,
      "itemBias": 0.8,
      "maxSelectMargin": 0.15
    }
  },
  "battleRules": {
    "maxItemUses": 3
  },
  "bag": [
    {
      "item": "cobblemon:potion",
      "quantity": 3
    }
  ],
  "team": [
    {
      "moveset": [
        "leechseed",
        "megadrain",
        "poisonpowder",
        "tailwind"
      ],
      "ivs": {
        "spe": 31,
        "spd": 31,
        "spa": 31,
        "def": 31,
        "atk": 31,
        "hp": 31
      },
      "evs": {},
      "species": "cottonee",
      "level": 16,
      "nature": "timid",
      "ability": "prankster",
      "heldItem": [
        "miracleseed"
      ],
      "gender": "FEMALE"
    },
    {
      "moveset": [
        "vinewhip",
        "lowkick",
        "taunt",
        "scratch"
      ],
      "ivs": {
        "spe": 31,
        "spd": 31,
        "spa": 31,
        "def": 31,
        "atk": 31,
        "hp": 31
      },
      "evs": {},
      "species": "pansage",
      "level": 17,
      "nature": "jolly",
      "ability": "gluttony",
      "heldItem": [
        "sitrusberry"
      ],
      "gender": "MALE"
    },
    {
      "moveset": [
        "razorleaf",
        "stringshot",
        "tackle",
        "bugbite"
      ],
      "ivs": {
        "spe": 31,
        "spd": 31,
        "spa": 31,
        "def": 31,
        "atk": 31,
        "hp": 31
      },
      "evs": {},
      "species": "sewaddle",
      "level": 18,
      "nature": "adamant",
      "ability": "swarm",
      "heldItem": [
        "oranberry"
      ],
      "gender": "MALE"
    }
  ],
  "battleFormat": "GEN_9_SINGLES"
}